helloto/__init__.py
helloto/main.py
helloto-1.0.1.dist-info/licenses/LICENSE
helloto-1.0.1.dist-info/METADATA
helloto-1.0.1.dist-info/WHEEL
helloto-1.0.1.dist-info/entry_points.txt
helloto-1.0.1.dist-info/top_level.txt
helloto-1.0.1.dist-info/RECORD
