Metadata-Version: 2.4
Name: helloto
Version: 1.0.1
Summary: For saying hello.
Author: Lunethra
License-File: LICENSE
Requires-Dist: typer[all]
Requires-Dist: rich
Requires-Dist: pyfiglet
Dynamic: license-file
